colors/__init__.py
colors/palette.py
colors/palettes/__init__.py
colors/palettes/copic.py
colors/palettes/dulux.py
colors/palettes/ncs.py
colors/palettes/pantone.py
colors/palettes/prismacolor.py
colors/palettes/ral.py
colors/utils.py
we_love_colors-2.0.0b0.dist-info/entry_points.txt
we_love_colors-2.0.0b0.dist-info/LICENSE
we_love_colors-2.0.0b0.dist-info/WHEEL
we_love_colors-2.0.0b0.dist-info/METADATA
we_love_colors-2.0.0b0.dist-info/RECORD
