Metadata-Version: 2.1
Name: we-love-colors
Version: 2.0.0b0
Summary: PANTONE®, RAL®, Dulux®, Copic® and Prismacolor® color palettes for Scribus, GIMP & Inkscape, the Python way
Home-page: https://fundevogel.de
License: MIT
Keywords: colors,copic,dulux,gimp,inkscape,pantone,prismacolor,ral,scribus
Author: Fundevogel
Author-email: maschinenraum@fundevogel.de
Maintainer: Martin Folkers
Maintainer-email: hello@twobrain.io
Requires-Python: >=3.8,<4.0
Classifier: Development Status :: 5 - Production/Stable
Classifier: Environment :: Console
Classifier: Environment :: Web Environment
Classifier: Intended Audience :: Developers
Classifier: License :: OSI Approved :: MIT License
Classifier: Operating System :: OS Independent
Classifier: Programming Language :: Python :: 3
Classifier: Programming Language :: Python :: 3.8
Classifier: Programming Language :: Python :: 3.9
Classifier: Programming Language :: Python :: 3.10
Classifier: Programming Language :: Python :: 3.10
Classifier: Programming Language :: Python :: 3.11
Classifier: Programming Language :: Python :: 3.8
Classifier: Programming Language :: Python :: 3.9
Classifier: Programming Language :: SQL
Classifier: Topic :: Database
Classifier: Topic :: Internet :: WWW/HTTP
Classifier: Topic :: Software Development :: Libraries :: Python Modules
Requires-Dist: beautifulsoup4 (>=4,<5)
Requires-Dist: click (>=8,<9)
Requires-Dist: lxml (>=4,<5)
Requires-Dist: pillow (>=9,<10)
Requires-Dist: requests (>=2,<3)
Project-URL: Funding, https://donate.rsf.org
Project-URL: Issue Tracker, https://codeberg.org/fundevogel/we-love-colors/issues
Project-URL: Repository, https://codeberg.org/fundevogel/we-love-colors
